[
  {
    "fact": "Sverige tar VM-brons i fotboll i USA.",
    "image": "1994_FIFA_World_Cup.svg",
    "pageViews": 420000,
    "qid": "Q101751",
    "subtitle": "Svenskt fotbollsminne",
    "title": "Sverige tar VM-brons i fotboll",
    "wikipediaSlug": "V%C3%A4rldsm%C3%A4sterskapet_i_fotboll_1994",
    "year": 1994
  },
  {
    "fact": "Zlatan Ibrahimović lämnar Inter för Barcelona.",
    "image": "Zlatan_Ibrahimović_June_2018.jpg",
    "pageViews": 380000,
    "qid": "Q46896",
    "subtitle": "Svensk spelarövergång",
    "title": "Zlatan går till Barcelona",
    "wikipediaSlug": "Zlatan_Ibrahimovi%C4%87",
    "year": 2009
  },
  {
    "fact": "Sverige spelar VM-final i fotboll på Råsunda mot Brasilien.",
    "image": "Pele_con_brasil_(cropped).jpg",
    "pageViews": 360000,
    "qid": "Q132533",
    "subtitle": "Fotbolls-VM på hemmaplan",
    "title": "Sverige spelar VM-final i fotboll",
    "wikipediaSlug": "V%C3%A4rldsm%C3%A4sterskapet_i_fotboll_1958",
    "year": 1958
  },
  {
    "fact": "Tre Kronor tar OS-guld i ishockey efter Peter Forsbergs berömda straff.",
    "image": "Peter_Forsberg_2016-03-17_001_(cropped).jpg",
    "pageViews": 320000,
    "qid": "Q653041",
    "subtitle": "Svenskt ishockeyminne",
    "title": "Tre Kronor tar OS-guld",
    "wikipediaSlug": "Ishockey_vid_olympiska_vinterspelen_1994",
    "year": 1994
  },
  {
    "fact": "Det första Vasaloppet körs.",
    "image": "Jørgen_Aukland_Vasaloppet_2013_001.jpg",
    "pageViews": 300000,
    "qid": "Q615072",
    "subtitle": "Svenskt skidlopp",
    "title": "Första Vasaloppet körs",
    "wikipediaSlug": "Vasaloppet",
    "year": 1922
  },
  {
    "fact": "Björn Borg vinner Wimbledon för första gången.",
    "image": "Björn_Borg_2013-11-06_001_(cropped).jpg",
    "pageViews": 300000,
    "qid": "Q104506",
    "subtitle": "Svensk tennisspelare",
    "title": "Björn Borg vinner Wimbledon",
    "wikipediaSlug": "Bj%C3%B6rn_Borg",
    "year": 1976
  },
  {
    "fact": "Armand Duplantis sätter världsrekord i stavhopp.",
    "image": "Armand_Duplantis_after_his_6.0_m_jump-1.jpg",
    "pageViews": 300000,
    "qid": "Q20740797",
    "subtitle": "Svenskt friidrottsminne",
    "title": "Duplantis sätter världsrekord",
    "wikipediaSlug": "Armand_Duplantis",
    "year": 2020
  },
  {
    "fact": "Ingemar Stenmark vinner OS-guld.",
    "image": "Ingemar_Stenmark,_June_2014-P6170012-1.jpg",
    "pageViews": 260000,
    "qid": "Q530",
    "subtitle": "Svensk alpin skidåkare",
    "title": "Ingemar Stenmark vinner OS-guld",
    "wikipediaSlug": "Ingemar_Stenmark",
    "year": 1980
  },
  {
    "fact": "Globen invigs i Stockholm.",
    "image": "Globen_från_Hammarbybacken,_2016a.jpg",
    "pageViews": 260000,
    "qid": "Q32926",
    "subtitle": "Arena i Stockholm",
    "title": "Globen invigs",
    "wikipediaSlug": "Globen",
    "year": 1989
  },
  {
    "fact": "Peter Forsberg avgör OS-finalen på straff.",
    "image": "Peter_Forsberg_2016-03-17_001_(cropped).jpg",
    "pageViews": 260000,
    "qid": "Q348416",
    "subtitle": "Svensk ishockeyspelare",
    "title": "Peter Forsberg avgör OS-finalen",
    "wikipediaSlug": "Peter_Forsberg",
    "year": 1994
  },
  {
    "fact": "Charlotte Kalla vinner OS-guld.",
    "image": "20190228_FIS_NWSC_Seefeld_Medal_Ceremony_Team_Sweden_850_5868_Charlotte_Kalla.jpg",
    "pageViews": 260000,
    "qid": "Q233270",
    "subtitle": "Svensk längdskidåkare",
    "title": "Charlotte Kalla vinner OS-guld",
    "wikipediaSlug": "Charlotte_Kalla",
    "year": 2010
  },
  {
    "fact": "Sarah Sjöström vinner OS-guld på 100 meter fjärilsim.",
    "image": "Sarah_Sjöström_2013.jpg",
    "pageViews": 260000,
    "qid": "Q235315",
    "subtitle": "Svenskt simminne",
    "title": "Sarah Sjöström vinner OS-guld",
    "wikipediaSlug": "Sarah_Sj%C3%B6str%C3%B6m",
    "year": 2016
  },
  {
    "fact": "Nils van der Poel vinner OS-guld.",
    "image": "Nils_van_der_Poel_in_2022.jpg",
    "pageViews": 260000,
    "qid": "Q15615329",
    "subtitle": "Svensk skridskoåkare",
    "title": "Nils van der Poel vinner OS-guld",
    "wikipediaSlug": "Nils_van_der_Poel",
    "year": 2022
  },
  {
    "fact": "Sverige tar OS-guld i ishockey i Turin med flera NHL-stjärnor i laget.",
    "image": "Henrik_Lundqvist_awarded_as_the_best_goalie_of_all_time_in_Swedish_hockey-2.jpg",
    "pageViews": 250000,
    "qid": "Q362157",
    "subtitle": "Svenskt ishockeyminne",
    "title": "Tre Kronor tar OS-guld igen",
    "wikipediaSlug": "Henrik_Lundqvist",
    "year": 2006
  },
  {
    "fact": "Sverige tar silver i damernas fotbolls-VM efter final mot Tyskland.",
    "image": "Victoria_Svensson.jpg",
    "pageViews": 240000,
    "qid": "Q500308",
    "subtitle": "Svenskt damlandslagsminne",
    "title": "Sverige spelar VM-final i damfotboll",
    "wikipediaSlug": "V%C3%A4rldsm%C3%A4sterskapet_i_fotboll_f%C3%B6r_damer_2003",
    "year": 2003
  },
  {
    "fact": "Ullevi invigs i Göteborg.",
    "image": "Nya_Ullevi_2013-07-06_001.jpg",
    "pageViews": 220000,
    "qid": "Q824352",
    "subtitle": "Svensk arena",
    "title": "Ullevi invigs",
    "wikipediaSlug": "Ullevi",
    "year": 1958
  },
  {
    "fact": "Ingemar Johansson blir världsmästare i tungviktsboxning.",
    "image": "Ingemar_Johansson_1960.jpg",
    "pageViews": 220000,
    "qid": "Q335872",
    "subtitle": "Svensk boxare",
    "title": "Ingemar Johansson blir världsmästare",
    "wikipediaSlug": "Ingemar_Johansson",
    "year": 1959
  },
  {
    "fact": "Börje Salming debuterar i NHL.",
    "image": "BorjeSalming2012.jpg",
    "pageViews": 220000,
    "qid": "Q739746",
    "subtitle": "Svensk ishockeyspelare",
    "title": "Börje Salming NHL-debuterar",
    "wikipediaSlug": "B%C3%B6rje_Salming",
    "year": 1973
  },
  {
    "fact": "Gunde Svan vinner OS-guld.",
    "image": "20190225_Seefeld_3347_Gunde_Svan.jpg",
    "pageViews": 220000,
    "qid": "Q357142",
    "subtitle": "Svensk längdskidåkare",
    "title": "Gunde Svan vinner OS-guld",
    "wikipediaSlug": "Gunde_Svan",
    "year": 1984
  },
  {
    "fact": "Mats Sundin blir första europé att väljas först i NHL-draften.",
    "image": "Mats_Sundin_in_feb_2015.jpg",
    "pageViews": 220000,
    "qid": "Q368528",
    "subtitle": "Svensk ishockeyspelare",
    "title": "Mats Sundin blir draftad först",
    "wikipediaSlug": "Mats_Sundin",
    "year": 1989
  },
  {
    "fact": "Jan-Ove Waldner vinner OS-guld i bordtennis.",
    "image": "Jan-Ove_Waldner.JPG",
    "pageViews": 220000,
    "qid": "Q345360",
    "subtitle": "Svensk bordtennisspelare",
    "title": "Jan-Ove Waldner vinner OS-guld",
    "wikipediaSlug": "Jan-Ove_Waldner",
    "year": 1992
  },
  {
    "fact": "Annika Sörenstam vinner US Open.",
    "image": "AnnikaStAndrews.JPG",
    "pageViews": 220000,
    "qid": "Q232711",
    "subtitle": "Svensk golfspelare",
    "title": "Annika Sörenstam vinner US Open",
    "wikipediaSlug": "Annika_S%C3%B6renstam",
    "year": 1995
  },
  {
    "fact": "Stefan Holm vinner OS-guld.",
    "image": "Stefan_Holm_2013.jpg",
    "pageViews": 220000,
    "qid": "Q311360",
    "subtitle": "Svensk höjdhoppare",
    "title": "Stefan Holm vinner OS-guld",
    "wikipediaSlug": "Stefan_Holm",
    "year": 2004
  },
  {
    "fact": "Carolina Klüft vinner OS-guld i sjukamp i Aten.",
    "image": "Carolina_Klüft_in_2025-4-2.jpg",
    "pageViews": 220000,
    "qid": "Q223672",
    "subtitle": "Svensk friidrottsklassiker",
    "title": "Carolina Klüft vinner OS-guld",
    "wikipediaSlug": "Carolina_Kl%C3%BCft",
    "year": 2004
  },
  {
    "fact": "Anja Pärson vinner OS-guld.",
    "image": "Anja_Pärson_Semmering_2008.jpg",
    "pageViews": 220000,
    "qid": "Q1933",
    "subtitle": "Svensk alpin skidåkare",
    "title": "Anja Pärson vinner OS-guld",
    "wikipediaSlug": "Anja_P%C3%A4rson",
    "year": 2006
  },
  {
    "fact": "Friends Arena invigs.",
    "image": "Strawberry_Arena.jpg",
    "pageViews": 220000,
    "qid": "Q1138684",
    "subtitle": "Svensk fotbollsarena",
    "title": "Friends Arena invigs",
    "wikipediaSlug": "Strawberry_Arena",
    "year": 2012
  },
  {
    "fact": "Henrik Stenson vinner The Open Championship.",
    "image": "Henrik_Stenson_in_Jan_2014.jpg",
    "pageViews": 220000,
    "qid": "Q1343639",
    "subtitle": "Svensk golfspelare",
    "title": "Henrik Stenson vinner The Open",
    "wikipediaSlug": "Henrik_Stenson",
    "year": 2016
  },
  {
    "fact": "Thomas Wassberg vinner OS-guld.",
    "image": "Thomas_Wassberg_2013-12-11_001.jpg",
    "pageViews": 200000,
    "qid": "Q195578",
    "subtitle": "Svensk längdskidåkare",
    "title": "Thomas Wassberg vinner OS-guld",
    "wikipediaSlug": "Thomas_Wassberg",
    "year": 1980
  },
  {
    "fact": "Pernilla Wiberg vinner OS-guld.",
    "image": "Pernilla_Wiberg_2011-12-06_001.jpg",
    "pageViews": 200000,
    "qid": "Q234886",
    "subtitle": "Svensk alpin skidåkare",
    "title": "Pernilla Wiberg vinner OS-guld",
    "wikipediaSlug": "Pernilla_Wiberg",
    "year": 1992
  },
  {
    "fact": "Stockholms stadion invigs.",
    "image": "Stockholm_Stadion_aerial.jpg",
    "pageViews": 180000,
    "qid": "Q727078",
    "subtitle": "Svensk idrottsarena",
    "title": "Stockholms stadion invigs",
    "wikipediaSlug": "Stockholms_stadion",
    "year": 1912
  },
  {
    "fact": "Råsunda fotbollsstadion invigs.",
    "image": "Råsunda_February_2013_01.jpg",
    "pageViews": 180000,
    "qid": "Q725623",
    "subtitle": "Svensk fotbollsarena",
    "title": "Råsunda invigs",
    "wikipediaSlug": "R%C3%A5sunda_fotbollsstadion",
    "year": 1937
  },
  {
    "fact": "Therese Alshammar tar VM-guld.",
    "image": "Therese_Alshammar_2013-01-08_001_(cropped).jpg",
    "pageViews": 180000,
    "qid": "Q272910",
    "subtitle": "Svensk simmare",
    "title": "Therese Alshammar tar VM-guld",
    "wikipediaSlug": "Therese_Alshammar",
    "year": 1999
  },
  {
    "qid": "Q211903",
    "title": "Henrik Larsson föds",
    "subtitle": "Svensk fotbollsspelare",
    "year": 1971,
    "fact": "Henrik Larsson föds.",
    "wikipediaSlug": "Henrik_Larsson",
    "image": "Henrik Larsson 2006.jpg",
    "pageViews": 26000
  },
  {
    "qid": "Q312450",
    "title": "Peter Forsberg föds",
    "subtitle": "Svensk ishockeyspelare",
    "year": 1973,
    "fact": "Peter Forsberg föds.",
    "wikipediaSlug": "Peter_Forsberg",
    "image": "Peter Forsberg 2012-12-29.JPG",
    "pageViews": 26000
  },
  {
    "qid": "Q312640",
    "title": "Henrik Lundqvist föds",
    "subtitle": "Svensk ishockeymålvakt",
    "year": 1982,
    "fact": "Henrik Lundqvist föds.",
    "wikipediaSlug": "Henrik_Lundqvist",
    "image": "Henrik Lundqvist 2014-05-29.jpg",
    "pageViews": 25000
  },
  {
    "qid": "Q312643",
    "title": "Sarah Sjöström föds",
    "subtitle": "Svensk simmare",
    "year": 1993,
    "fact": "Sarah Sjöström föds.",
    "wikipediaSlug": "Sarah_Sj%C3%B6str%C3%B6m",
    "image": "Sarah Sjöström 2015.jpg",
    "pageViews": 24000
  },
  {
    "qid": "Q106581",
    "title": "Friends Arena öppnar",
    "subtitle": "Nationalarena i Solna",
    "year": 2012,
    "fact": "Friends Arena öppnar.",
    "wikipediaSlug": "Friends_Arena",
    "image": "Friends Arena 2013.jpg",
    "pageViews": 16000
  },
  {
    "qid": "Q220505",
    "title": "Ullevi öppnar",
    "subtitle": "Arena i Göteborg",
    "year": 1958,
    "fact": "Ullevi öppnar.",
    "wikipediaSlug": "Ullevi",
    "image": "Ullevi stadium 2006.jpg",
    "pageViews": 15000
  }
]
